htcondor_dags/__init__.py
htcondor_dags/dag.py
htcondor_dags/edges.py
htcondor_dags/exceptions.py
htcondor_dags/formatter.py
htcondor_dags/node.py
htcondor_dags/rescue.py
htcondor_dags/utils.py
htcondor_dags/version.py
htcondor_dags/walk_order.py
htcondor_dags/writer.py
htcondor_dags-0.2.0.dist-info/LICENSE
htcondor_dags-0.2.0.dist-info/METADATA
htcondor_dags-0.2.0.dist-info/WHEEL
htcondor_dags-0.2.0.dist-info/top_level.txt
htcondor_dags-0.2.0.dist-info/RECORD
