Metadata-Version: 2.1
Name: htcondor-dags
Version: 0.2.0
Summary: High-level tools for writing HTCondor DAGfiles
Home-page: https://github.com/htcondor/htcondor-dags
Author: Josh Karpel
Author-email: josh.karpel@gmail.com
License: ASL 2.0
Platform: UNKNOWN
Classifier: License :: OSI Approved :: Apache Software License
Classifier: Development Status :: 3 - Alpha
Classifier: Programming Language :: Python :: 3
Classifier: Intended Audience :: Science/Research
Classifier: Intended Audience :: Developers
Classifier: Operating System :: OS Independent
Classifier: Programming Language :: Python :: 3 :: Only
Classifier: Programming Language :: Python :: 3.6
Classifier: Programming Language :: Python :: 3.7
Classifier: Programming Language :: Python :: 3.8
Classifier: Topic :: System :: Distributed Computing
Requires-Dist: htcondor (>=8.8.0)
